[{"home": "Fribourg", "away": "Bayer Leverkusen", "time": "", "league": "Bundesliga", "country": "ALLEMAGNE", "score": {"home": "2", "away": "1"}, "Day": "19/12", "Ended": true}, {"home": "FC Cologne", "away": "Stuttgart", "time": "", "league": "Bundesliga", "country": "ALLEMAGNE", "score": {"home": "1", "away": "0"}, "Day": "19/12", "Ended": true}, {"home": "Everton", "away": "Leicester", "time": "", "league": "Premier League", "country": "ANGLETERRE", "score": {"home": "-", "away": "-"}, "Day": "19/12", "Ended": false}, {"home": "Newcastle", "away": "Manchester City", "time": "", "league": "Premier League", "country": "ANGLETERRE", "score": {"home": "0", "away": "4"}, "Day": "19/12", "Ended": true}, {"home": "Wolves", "away": "Chelsea", "time": "", "league": "Premier League", "country": "ANGLETERRE", "score": {"home": "0", "away": "0"}, "Day": "19/12", "Ended": true}, {"home": "Tottenham", "away": "Liverpool", "time": "", "league": "Premier League", "country": "ANGLETERRE", "score": {"home": "2", "away": "2"}, "Day": "19/12", "Ended": true}, {"home": "Grenade", "away": "Majorque", "time": "", "league": "LaLiga", "country": "ESPAGNE", "score": {"home": "4", "away": "1"}, "Day": "19/12", "Ended": true}, {"home": "Ath. Bilbao", "away": "Betis", "time": "", "league": "LaLiga", "country": "ESPAGNE", "score": {"home": "3", "away": "2"}, "Day": "19/12", "Ended": true}, {"home": "Getafe", "away": "Osasuna", "time": "", "league": "LaLiga", "country": "ESPAGNE", "score": {"home": "1", "away": "0"}, "Day": "19/12", "Ended": true}, {"home": "Real Madrid", "away": "Cadix CF", "time": "", "league": "LaLiga", "country": "ESPAGNE", "score": {"home": "0", "away": "0"}, "Day": "19/12", "Ended": false}, {"home": "Bergerac", "away": "Metz", "time": "", "league": "Coupe de France", "country": "FRANCE", "score": {"home": "1", "away": "0"}, "Day": "19/12", "Ended": false}, {"home": "Lyon - La Duchère", "away": "Saint-Étienne", "time": "", "league": "Coupe de France", "country": "FRANCE", "score": {"home": "0", "away": "1"}, "Day": "19/12", "Ended": true}, {"home": "Marseille", "away": "Cannet Rocheville", "time": "", "league": "Coupe de France", "country": "FRANCE", "score": {"home": "4", "away": "1"}, "Day": "19/12", "Ended": true}, {"home": "Red Star", "away": "Monaco", "time": "", "league": "Coupe de France", "country": "FRANCE", "score": {"home": "0", "away": "2"}, "Day": "19/12", "Ended": true}, {"home": "Stade Poitevin", "away": "Lens", "time": "", "league": "Coupe de France", "country": "FRANCE", "score": {"home": "0", "away": "1"}, "Day": "19/12", "Ended": true}, {"home": "Andrézieux", "away": "Montpellier", "time": "", "league": "Coupe de France", "country": "FRANCE", "score": {"home": "0", "away": "1"}, "Day": "19/12", "Ended": true}, {"home": "Linas-Montlhery", "away": "Angers", "time": "", "league": "Coupe de France", "country": "FRANCE", "score": {"home": "2", "away": "0"}, "Day": "19/12", "Ended": true}, {"home": "Reims Sainte-Anne", "away": "Reims", "time": "", "league": "Coupe de France", "country": "FRANCE", "score": {"home": "0", "away": "1"}, "Day": "19/12", "Ended": true}, {"home": "Wasquehal", "away": "Vannes", "time": "", "league": "Coupe de France", "country": "FRANCE", "score": {"home": "0", "away": "4"}, "Day": "19/12", "Ended": true}, {"home": "Bordeaux", "away": "Jumeaux M'Zouazia", "time": "", "league": "Coupe de France", "country": "FRANCE", "score": {"home": "10", "away": "0"}, "Day": "19/12", "Ended": true}, {"home": "Chauvigny", "away": "Chartres", "time": "", "league": "Coupe de France", "country": "FRANCE", "score": {"home": "2", "away": "1"}, "Day": "19/12", "Ended": true}, {"home": "Cholet", "away": "Nice", "time": "", "league": "Coupe de France", "country": "FRANCE", "score": {"home": "0", "away": "1"}, "Day": "19/12", "Ended": true}, {"home": "Dinan Léhon", "away": "Brest", "time": "", "league": "Coupe de France", "country": "FRANCE", "score": {"home": "0", "away": "1"}, "Day": "19/12", "Ended": false}, {"home": "Montauban", "away": "La Roche-sur-Yon", "time": "", "league": "Coupe de France", "country": "FRANCE", "score": {"home": "1", "away": "2"}, "Day": "19/12", "Ended": true}, {"home": "Feignies-Aulnoye", "away": "PSG", "time": "", "league": "Coupe de France", "country": "FRANCE", "score": {"home": "0", "away": "1"}, "Day": "19/12", "Ended": false}, {"home": "Fiorentina", "away": "Sassuolo", "time": "", "league": "Serie A", "country": "ITALIE", "score": {"home": "2", "away": "2"}, "Day": "19/12", "Ended": true}, {"home": "Spezia", "away": "Empoli", "time": "", "league": "Serie A", "country": "ITALIE", "score": {"home": "1", "away": "1"}, "Day": "19/12", "Ended": true}, {"home": "Sampdoria", "away": "Venezia", "time": "", "league": "Serie A", "country": "ITALIE", "score": {"home": "1", "away": "1"}, "Day": "19/12", "Ended": true}, {"home": "Torino", "away": "Hellas Vérone", "time": "", "league": "Serie A", "country": "ITALIE", "score": {"home": "1", "away": "0"}, "Day": "19/12", "Ended": true}, {"home": "AC Milan", "away": "Naples", "time": "", "league": "Serie A", "country": "ITALIE", "score": {"home": "0", "away": "1"}, "Day": "19/12", "Ended": false}, {"home": "Cambuur", "away": "Heerenveen", "time": "", "league": "Eredivisie", "country": "PAYS-BAS", "score": {"home": "1", "away": "2"}, "Day": "19/12", "Ended": true}, {"home": "Feyenoord", "away": "Ajax", "time": "", "league": "Eredivisie", "country": "PAYS-BAS", "score": {"home": "0", "away": "2"}, "Day": "19/12", "Ended": true}, {"home": "G.A. Eagles", "away": "Nijmegen", "time": "", "league": "Eredivisie", "country": "PAYS-BAS", "score": {"home": "0", "away": "2"}, "Day": "19/12", "Ended": true}, {"home": "Waalwijk", "away": "PSV", "time": "", "league": "Eredivisie", "country": "PAYS-BAS", "score": {"home": "1", "away": "4"}, "Day": "19/12", "Ended": true}, {"home": "Royal AM", "away": "Kaizer", "time": "", "league": "Premier Soccer League", "country": "AFRIQUE DU SUD", "score": {"home": "1", "away": "0"}, "Day": "19/12", "Ended": true}, {"home": "Maritzburg Utd", "away": "Chippa United", "time": "", "league": "Premier Soccer League", "country": "AFRIQUE DU SUD", "score": {"home": "0", "away": "2"}, "Day": "19/12", "Ended": true}, {"home": "Egnatia", "away": "Laci", "time": "", "league": "Superliga", "country": "ALBANIE", "score": {"home": "0", "away": "2"}, "Day": "19/12", "Ended": true}, {"home": "Kukesi", "away": "Partizani", "time": "", "league": "Superliga", "country": "ALBANIE", "score": {"home": "2", "away": "1"}, "Day": "19/12", "Ended": true}, {"home": "Tirana", "away": "Teuta", "time": "", "league": "Superliga", "country": "ALBANIE", "score": {"home": "2", "away": "1"}, "Day": "19/12", "Ended": true}, {"home": "Hanovre", "away": "Werder Brême", "time": "", "league": "2. Bundesliga", "country": "ALLEMAGNE", "score": {"home": "1", "away": "4"}, "Day": "19/12", "Ended": true}, {"home": "Karlsruher", "away": "Rostock", "time": "", "league": "2. Bundesliga", "country": "ALLEMAGNE", "score": {"home": "2", "away": "2"}, "Day": "19/12", "Ended": true}, {"home": "Regensburg", "away": "Darmstadt", "time": "", "league": "2. Bundesliga", "country": "ALLEMAGNE", "score": {"home": "0", "away": "2"}, "Day": "19/12", "Ended": true}, {"home": "Magdeburg", "away": "Mannheim", "time": "", "league": "3. Liga", "country": "ALLEMAGNE", "score": {"home": "3", "away": "0"}, "Day": "19/12", "Ended": true}, {"home": "Duisburg", "away": "Osnabruck", "time": "", "league": "3. Liga", "country": "ALLEMAGNE", "score": {"home": "0", "away": "0"}, "Day": "19/12", "Ended": false}, {"home": "BFC Dynamo", "away": "Eilenburg", "time": "", "league": "Regionalliga Nordost", "country": "ALLEMAGNE", "score": {"home": "6", "away": "0"}, "Day": "19/12", "Ended": true}, {"home": "Furstenwalde", "away": "Chemnitzer", "time": "", "league": "Regionalliga Nordost", "country": "ALLEMAGNE", "score": {"home": "1", "away": "3"}, "Day": "19/12", "Ended": true}, {"home": "Lichtenberg", "away": "Babelsberg", "time": "", "league": "Regionalliga Nordost", "country": "ALLEMAGNE", "score": {"home": "0", "away": "1"}, "Day": "19/12", "Ended": true}, {"home": "Bayer Leverkusen F", "away": "Jena F", "time": "", "league": "Bundesliga - Femmes", "country": "ALLEMAGNE", "score": {"home": "2", "away": "0"}, "Day": "19/12", "Ended": true}, {"home": "Sand F", "away": "Eintracht Frankfurt F", "time": "", "league": "Bundesliga - Femmes", "country": "ALLEMAGNE", "score": {"home": "0", "away": "2"}, "Day": "19/12", "Ended": true}, {"home": "Potsdam F", "away": "Wolfsburg F", "time": "", "league": "Bundesliga - Femmes", "country": "ALLEMAGNE", "score": {"home": "-", "away": "-"}, "Day": "19/12", "Ended": false}, {"home": "Werder Brême F", "away": "Bayern Munich F", "time": "", "league": "Bundesliga - Femmes", "country": "ALLEMAGNE", "score": {"home": "0", "away": "2"}, "Day": "19/12", "Ended": true}, {"home": "Atletic Escaldes", "away": "Ordino", "time": "", "league": "Primera Divisió", "country": "ANDORRE", "score": {"home": "3", "away": "0"}, "Day": "19/12", "Ended": true}, {"home": "Inter Escaldes", "away": "UE Santa Coloma", "time": "", "league": "Primera Divisió", "country": "ANDORRE", "score": {"home": "2", "away": "2"}, "Day": "19/12", "Ended": true}, {"home": "FC Santa Coloma", "away": "Carroi", "time": "", "league": "Primera Divisió", "country": "ANDORRE", "score": {"home": "3", "away": "0"}, "Day": "19/12", "Ended": true}, {"home": "Sant Julia", "away": "UE Engordany", "time": "", "league": "Primera Divisió", "country": "ANDORRE", "score": {"home": "3", "away": "2"}, "Day": "19/12", "Ended": true}, {"home": "Colon", "away": "River Plate", "time": "", "league": "Trofeo de Campeones", "country": "ARGENTINE", "score": {"home": "0", "away": "4"}, "Day": "19/12", "Ended": true}, {"home": "Britannia", "away": "Dakota", "time": "", "league": "Division di Honor", "country": "ARUBA", "score": {"home": "3", "away": "2"}, "Day": "19/12", "Ended": true}, {"home": "Estrella", "away": "Bubali", "time": "23:00", "league": "Division di Honor", "country": "ARUBA", "score": {"home": "-", "away": "-"}, "Day": "19/12", "Ended": "unKnown"}, {"home": "Malaisie", "away": "Indonésie", "time": "", "league": "AFF Coupe Suzuki", "country": "ASIE", "score": {"home": "1", "away": "4"}, "Day": "19/12", "Ended": true}, {"home": "Vietnam", "away": "Cambodge", "time": "", "league": "AFF Coupe Suzuki", "country": "ASIE", "score": {"home": "4", "away": "0"}, "Day": "19/12", "Ended": true}, {"home": "Macarthur FC", "away": "Newcastle Jets", "time": "", "league": "A-League", "country": "AUSTRALIE", "score": {"home": "2", "away": "1"}, "Day": "19/12", "Ended": true}, {"home": "Sydney FC", "away": "Wellington Phoenix", "time": "", "league": "A-League", "country": "AUSTRALIE", "score": {"home": "2", "away": "1"}, "Day": "19/12", "Ended": true}, {"home": "Club Brugge", "away": "Anderlecht", "time": "", "league": "Pro League", "country": "BELGIQUE", "score": {"home": "2", "away": "2"}, "Day": "19/12", "Ended": true}, {"home": "Eupen", "away": "Charleroi", "time": "", "league": "Pro League", "country": "BELGIQUE", "score": {"home": "0", "away": "4"}, "Day": "19/12", "Ended": true}, {"home": "Genk", "away": "Antwerp", "time": "", "league": "Pro League", "country": "BELGIQUE", "score": {"home": "1", "away": "1"}, "Day": "19/12", "Ended": true}, {"home": "Louvain", "away": "Standard Liège", "time": "", "league": "Pro League", "country": "BELGIQUE", "score": {"home": "2", "away": "0"}, "Day": "19/12", "Ended": false}, {"home": "Lierse K.", "away": "RWDM", "time": "", "league": "D1B Pro League", "country": "BELGIQUE", "score": {"home": "0", "away": "1"}, "Day": "19/12", "Ended": true}, {"home": "Westerlo", "away": "Virton", "time": "", "league": "D1B Pro League", "country": "BELGIQUE", "score": {"home": "0", "away": "1"}, "Day": "19/12", "Ended": false}, {"home": "U. Sucre", "away": "Real Potosi", "time": "", "league": "Division Profesional - Relégation", "country": "BOLIVIE", "score": {"home": "1", "away": "0"}, "Day": "19/12", "Ended": false}, {"home": "Changchun Yatai", "away": "Guangzhou FC", "time": "", "league": "Super League - Groupe Championnat", "country": "CHINE", "score": {"home": "0", "away": "2"}, "Day": "19/12", "Ended": true}, {"home": "Shanghai Port", "away": "Shandong Taishan", "time": "", "league": "Super League - Groupe Championnat", "country": "CHINE", "score": {"home": "0", "away": "2"}, "Day": "19/12", "Ended": true}, {"home": "Guangzhou City", "away": "Beijing Guoan", "time": "", "league": "Super League - Groupe Championnat", "country": "CHINE", "score": {"home": "5", "away": "0"}, "Day": "19/12", "Ended": true}, {"home": "Shenzhen", "away": "Hebei", "time": "", "league": "Super League - Groupe Championnat", "country": "CHINE", "score": {"home": "3", "away": "0"}, "Day": "19/12", "Ended": true}, {"home": "AEL Limassol", "away": "Ol. Nicosia", "time": "", "league": "Première Division", "country": "CHYPRE", "score": {"home": "3", "away": "0"}, "Day": "19/12", "Ended": true}, {"home": "Doxa", "away": "Omonia", "time": "", "league": "Première Division", "country": "CHYPRE", "score": {"home": "2", "away": "1"}, "Day": "19/12", "Ended": true}, {"home": "Dragovoljac", "away": "Din. Zagreb", "time": "", "league": "1. HNL", "country": "CROATIE", "score": {"home": "0", "away": "2"}, "Day": "19/12", "Ended": true}, {"home": "Hajduk Split", "away": "Osijek", "time": "", "league": "1. HNL", "country": "CROATIE", "score": {"home": "0", "away": "0"}, "Day": "19/12", "Ended": true}, {"home": "Hibernian", "away": "Celtic", "time": "", "league": "League Cup - Phase Finale", "country": "ECOSSE", "score": {"home": "1", "away": "2"}, "Day": "19/12", "Ended": true}, {"home": "Fuenlabrada", "away": "R. Oviedo", "time": "", "league": "LaLiga2", "country": "ESPAGNE", "score": {"home": "0", "away": "0"}, "Day": "19/12", "Ended": true}, {"home": "Ponferradina", "away": "Amorebieta", "time": "", "league": "LaLiga2", "country": "ESPAGNE", "score": {"home": "1", "away": "1"}, "Day": "19/12", "Ended": true}, {"home": "Saragosse", "away": "Tenerife", "time": "", "league": "LaLiga2", "country": "ESPAGNE", "score": {"home": "0", "away": "2"}, "Day": "19/12", "Ended": true}, {"home": "Cartagena", "away": "Mirandes", "time": "", "league": "LaLiga2", "country": "ESPAGNE", "score": {"home": "3", "away": "0"}, "Day": "19/12", "Ended": true}, {"home": "Huesca", "away": "Alcorcon", "time": "", "league": "LaLiga2", "country": "ESPAGNE", "score": {"home": "0", "away": "0"}, "Day": "19/12", "Ended": true}, {"home": "R. Sociedad B", "away": "Valladolid", "time": "", "league": "LaLiga2", "country": "ESPAGNE", "score": {"home": "0", "away": "2"}, "Day": "19/12", "Ended": true}, {"home": "Ath. Bilbao B", "away": "San Sebastian Reyes", "time": "", "league": "Primera RFEF - Group 1", "country": "ESPAGNE", "score": {"home": "0", "away": "2"}, "Day": "19/12", "Ended": true}, {"home": "CF Talavera", "away": "R. Union", "time": "", "league": "Primera RFEF - Group 1", "country": "ESPAGNE", "score": {"home": "1", "away": "3"}, "Day": "19/12", "Ended": true}, {"home": "Tudelano", "away": "Celta Vigo B", "time": "", "league": "Primera RFEF - Group 1", "country": "ESPAGNE", "score": {"home": "2", "away": "0"}, "Day": "19/12", "Ended": true}, {"home": "Unionistas", "away": "UD Logrones", "time": "", "league": "Primera RFEF - Group 1", "country": "ESPAGNE", "score": {"home": "4", "away": "0"}, "Day": "19/12", "Ended": true}, {"home": "Rayo Majadahonda", "away": "Badajoz", "time": "", "league": "Primera RFEF - Group 1", "country": "ESPAGNE", "score": {"home": "-", "away": "-"}, "Day": "19/12", "Ended": false}, {"home": "Valladolid Promesas", "away": "Zamora", "time": "", "league": "Primera RFEF - Group 1", "country": "ESPAGNE", "score": {"home": "1", "away": "3"}, "Day": "19/12", "Ended": true}, {"home": "Leonesa", "away": "La Corogne", "time": "", "league": "Primera RFEF - Group 1", "country": "ESPAGNE", "score": {"home": "2", "away": "3"}, "Day": "19/12", "Ended": true}, {"home": "Albacete", "away": "Algeciras", "time": "", "league": "Primera RFEF - Group 2", "country": "ESPAGNE", "score": {"home": "3", "away": "1"}, "Day": "19/12", "Ended": true}, {"home": "Baleares", "away": "San Fernando", "time": "", "league": "Primera RFEF - Group 2", "country": "ESPAGNE", "score": {"home": "-", "away": "-"}, "Day": "19/12", "Ended": false}, {"home": "Castellon", "away": "Sabadell", "time": "", "league": "Primera RFEF - Group 2", "country": "ESPAGNE", "score": {"home": "0", "away": "1"}, "Day": "19/12", "Ended": true}, {"home": "Linares", "away": "FC Séville B", "time": "", "league": "Primera RFEF - Group 2", "country": "ESPAGNE", "score": {"home": "4", "away": "0"}, "Day": "19/12", "Ended": true}, {"home": "Cornella", "away": "Barcelone B", "time": "", "league": "Primera RFEF - Group 2", "country": "ESPAGNE", "score": {"home": "1", "away": "0"}, "Day": "19/12", "Ended": true}, {"home": "Lille F", "away": "Orléans F", "time": "", "league": "Division 2 Féminine", "country": "FRANCE", "score": {"home": "3", "away": "0"}, "Day": "19/12", "Ended": true}, {"home": "Aduana", "away": "Berekum Chelsea", "time": "", "league": "Premier League", "country": "GHANA", "score": {"home": "3", "away": "2"}, "Day": "19/12", "Ended": true}, {"home": "Ashanti Gold", "away": "Great Olympics", "time": "", "league": "Premier League", "country": "GHANA", "score": {"home": "0", "away": "0"}, "Day": "19/12", "Ended": true}, {"home": "Eleven Wonders", "away": "Bibiani Gold Stars", "time": "", "league": "Premier League", "country": "GHANA", "score": {"home": "2", "away": "1"}, "Day": "19/12", "Ended": true}, {"home": "Karela", "away": "Bechem United", "time": "", "league": "Premier League", "country": "GHANA", "score": {"home": "1", "away": "1"}, "Day": "19/12", "Ended": true}, {"home": "Legon Cities", "away": "Asante Kotoko", "time": "", "league": "Premier League", "country": "GHANA", "score": {"home": "1", "away": "2"}, "Day": "19/12", "Ended": true}, {"home": "Tamale", "away": "Elmina Sharks", "time": "", "league": "Premier League", "country": "GHANA", "score": {"home": "2", "away": "0"}, "Day": "19/12", "Ended": true}, {"home": "WAFA", "away": "Medeama", "time": "", "league": "Premier League", "country": "GHANA", "score": {"home": "1", "away": "0"}, "Day": "19/12", "Ended": true}, {"home": "Hearts Of Oak", "away": "Accra Lions", "time": "", "league": "Premier League", "country": "GHANA", "score": {"home": "2", "away": "0"}, "Day": "19/12", "Ended": true}, {"home": "St Josephs", "away": "Manchester 62", "time": "", "league": "National League", "country": "GIBRALTAR", "score": {"home": "3", "away": "1"}, "Day": "19/12", "Ended": true}, {"home": "Lincoln", "away": "Magpies", "time": "", "league": "National League", "country": "GIBRALTAR", "score": {"home": "5", "away": "0"}, "Day": "19/12", "Ended": true}, {"home": "Olympiakos", "away": "Lamia", "time": "", "league": "Super League", "country": "GRÈCE", "score": {"home": "1", "away": "0"}, "Day": "19/12", "Ended": true}, {"home": "Volos", "away": "Smyrnis", "time": "", "league": "Super League", "country": "GRÈCE", "score": {"home": "-", "away": "-"}, "Day": "19/12", "Ended": false}, {"home": "Panathinaikos", "away": "Giannina", "time": "", "league": "Super League", "country": "GRÈCE", "score": {"home": "2", "away": "0"}, "Day": "19/12", "Ended": true}, {"home": "PAOK", "away": "Asteras T.", "time": "", "league": "Super League", "country": "GRÈCE", "score": {"home": "3", "away": "2"}, "Day": "19/12", "Ended": true}, {"home": "AEK B", "away": "O.F. Ierapetra", "time": "", "league": "Super League 2", "country": "GRÈCE", "score": {"home": "2", "away": "2"}, "Day": "19/12", "Ended": true}, {"home": "Almopos", "away": "Niki Volos", "time": "", "league": "Super League 2", "country": "GRÈCE", "score": {"home": "-", "away": "-"}, "Day": "19/12", "Ended": false}, {"home": "Episkopi", "away": "PAE Egaleo", "time": "", "league": "Super League 2", "country": "GRÈCE", "score": {"home": "1", "away": "1"}, "Day": "19/12", "Ended": true}, {"home": "Ergotelis", "away": "Asteras Vlachioti", "time": "", "league": "Super League 2", "country": "GRÈCE", "score": {"home": "0", "away": "0"}, "Day": "19/12", "Ended": true}, {"home": "Kalamata", "away": "Zakynthos", "time": "", "league": "Super League 2", "country": "GRÈCE", "score": {"home": "5", "away": "0"}, "Day": "19/12", "Ended": true}, {"home": "Karaiskakis", "away": "Diagoras", "time": "", "league": "Super League 2", "country": "GRÈCE", "score": {"home": "0", "away": "0"}, "Day": "19/12", "Ended": true}, {"home": "Karditsa", "away": "Apollon Larissa", "time": "", "league": "Super League 2", "country": "GRÈCE", "score": {"home": "1", "away": "0"}, "Day": "19/12", "Ended": true}, {"home": "Kavala", "away": "O. Volos", "time": "", "league": "Super League 2", "country": "GRÈCE", "score": {"home": "0", "away": "5"}, "Day": "19/12", "Ended": true}, {"home": "Kifisias", "away": "Kallithea", "time": "", "league": "Super League 2", "country": "GRÈCE", "score": {"home": "1", "away": "0"}, "Day": "19/12", "Ended": true}, {"home": "Pierikos", "away": "AEL Larissa", "time": "", "league": "Super League 2", "country": "GRÈCE", "score": {"home": "0", "away": "0"}, "Day": "19/12", "Ended": true}, {"home": "Rodos", "away": "Irodotos", "time": "", "league": "Super League 2", "country": "GRÈCE", "score": {"home": "1", "away": "0"}, "Day": "19/12", "Ended": true}, {"home": "Thesprotos", "away": "PAOK B", "time": "", "league": "Super League 2", "country": "GRÈCE", "score": {"home": "1", "away": "1"}, "Day": "19/12", "Ended": true}, {"home": "Xanthi", "away": "AO Trikala", "time": "", "league": "Super League 2", "country": "GRÈCE", "score": {"home": "5", "away": "0"}, "Day": "19/12", "Ended": true}, {"home": "Antigua", "away": "Solola", "time": "", "league": "Liga Nacional - Ouverture - Phase Finale", "country": "GUATEMALA", "score": {"home": "5", "away": "1"}, "Day": "19/12", "Ended": true}, {"home": "Comunicaciones", "away": "Iztapa", "time": "", "league": "Liga Nacional - Ouverture - Phase Finale", "country": "GUATEMALA", "score": {"home": "1", "away": "0"}, "Day": "19/12", "Ended": true}, {"home": "Municipal", "away": "Xelaju", "time": "", "league": "Liga Nacional - Ouverture - Phase Finale", "country": "GUATEMALA", "score": {"home": "0", "away": "1"}, "Day": "19/12", "Ended": true}, {"home": "Malacateco", "away": "Santa Lucia", "time": "22:00", "league": "Liga Nacional - Ouverture - Phase Finale", "country": "GUATEMALA", "score": {"home": "-", "away": "-"}, "Day": "19/12", "Ended": "unKnown"}, {"home": "Olimpia", "away": "Real Espana", "time": "23:00", "league": "Liga Nacional - Ouverture - Phase Finale", "country": "HONDURAS", "score": {"home": "-", "away": "-"}, "Day": "19/12", "Ended": "unKnown"}, {"home": "Kisvarda", "away": "Puskas Academy", "time": "", "league": "OTP Bank Liga", "country": "HONGRIE", "score": {"home": "1", "away": "1"}, "Day": "19/12", "Ended": true}, {"home": "Gyirmot", "away": "Debrecen", "time": "", "league": "OTP Bank Liga", "country": "HONGRIE", "score": {"home": "0", "away": "0"}, "Day": "19/12", "Ended": true}, {"home": "Zalaegerszeg", "away": "Ujpest", "time": "", "league": "OTP Bank Liga", "country": "HONGRIE", "score": {"home": "2", "away": "0"}, "Day": "19/12", "Ended": true}, {"home": "Mumbai City", "away": "Kerala Blasters", "time": "", "league": "ISL", "country": "INDE", "score": {"home": "0", "away": "3"}, "Day": "19/12", "Ended": true}, {"home": "Alessandria", "away": "Parme", "time": "", "league": "Serie B", "country": "ITALIE", "score": {"home": "0", "away": "2"}, "Day": "19/12", "Ended": true}, {"home": "Brescia", "away": "Cittadella", "time": "", "league": "Serie B", "country": "ITALIE", "score": {"home": "1", "away": "1"}, "Day": "19/12", "Ended": true}, {"home": "Perugia", "away": "Ternana", "time": "", "league": "Serie B", "country": "ITALIE", "score": {"home": "1", "away": "1"}, "Day": "19/12", "Ended": true}, {"home": "Benevento", "away": "Monza", "time": "", "league": "Serie B", "country": "ITALIE", "score": {"home": "-", "away": "-"}, "Day": "19/12", "Ended": false}, {"home": "Grosseto", "away": "Olbia", "time": "", "league": "Serie C - Groupe B", "country": "ITALIE", "score": {"home": "0", "away": "1"}, "Day": "19/12", "Ended": true}, {"home": "Viterbese", "away": "Carrarese", "time": "", "league": "Serie C - Groupe B", "country": "ITALIE", "score": {"home": "0", "away": "0"}, "Day": "19/12", "Ended": true}, {"home": "Ancona-Matelica", "away": "Vis Pesaro", "time": "", "league": "Serie C - Groupe B", "country": "ITALIE", "score": {"home": "3", "away": "1"}, "Day": "19/12", "Ended": true}, {"home": "Cesena", "away": "Siena", "time": "", "league": "Serie C - Groupe B", "country": "ITALIE", "score": {"home": "1", "away": "0"}, "Day": "19/12", "Ended": true}, {"home": "Fermana", "away": "Entella", "time": "", "league": "Serie C - Groupe B", "country": "ITALIE", "score": {"home": "1", "away": "1"}, "Day": "19/12", "Ended": true}, {"home": "Gubbio", "away": "Montevarchi", "time": "", "league": "Serie C - Groupe B", "country": "ITALIE", "score": {"home": "1", "away": "0"}, "Day": "19/12", "Ended": true}, {"home": "Imolese", "away": "Pescara", "time": "", "league": "Serie C - Groupe B", "country": "ITALIE", "score": {"home": "0", "away": "1"}, "Day": "19/12", "Ended": true}, {"home": "Pistoiese", "away": "Lucchese", "time": "", "league": "Serie C - Groupe B", "country": "ITALIE", "score": {"home": "0", "away": "0"}, "Day": "19/12", "Ended": true}, {"home": "Pontedera", "away": "Modena", "time": "", "league": "Serie C - Groupe B", "country": "ITALIE", "score": {"home": "1", "away": "2"}, "Day": "19/12", "Ended": true}, {"home": "Reggiana", "away": "Teramo", "time": "", "league": "Serie C - Groupe B", "country": "ITALIE", "score": {"home": "5", "away": "0"}, "Day": "19/12", "Ended": true}, {"home": "ACR Messina", "away": "Catania", "time": "", "league": "Serie C - Groupe C", "country": "ITALIE", "score": {"home": "2", "away": "2"}, "Day": "19/12", "Ended": true}, {"home": "Avellino", "away": "Foggia", "time": "", "league": "Serie C - Groupe C", "country": "ITALIE", "score": {"home": "2", "away": "2"}, "Day": "19/12", "Ended": true}, {"home": "Catanzaro", "away": "Vibonese", "time": "", "league": "Serie C - Groupe C", "country": "ITALIE", "score": {"home": "1", "away": "1"}, "Day": "19/12", "Ended": true}, {"home": "Fidelis Andria", "away": "Monopoli", "time": "", "league": "Serie C - Groupe C", "country": "ITALIE", "score": {"home": "1", "away": "2"}, "Day": "19/12", "Ended": true}, {"home": "Latina", "away": "Monterosi FC", "time": "", "league": "Serie C - Groupe C", "country": "ITALIE", "score": {"home": "3", "away": "3"}, "Day": "19/12", "Ended": true}, {"home": "Paganese", "away": "Turris", "time": "", "league": "Serie C - Groupe C", "country": "ITALIE", "score": {"home": "1", "away": "1"}, "Day": "19/12", "Ended": true}, {"home": "Palerme", "away": "Bari", "time": "", "league": "Serie C - Groupe C", "country": "ITALIE", "score": {"home": "0", "away": "0"}, "Day": "19/12", "Ended": true}, {"home": "Potenza", "away": "Campobasso", "time": "", "league": "Serie C - Groupe C", "country": "ITALIE", "score": {"home": "0", "away": "1"}, "Day": "19/12", "Ended": true}, {"home": "Taranto", "away": "Picerno", "time": "", "league": "Serie C - Groupe C", "country": "ITALIE", "score": {"home": "2", "away": "0"}, "Day": "19/12", "Ended": true}, {"home": "Virtus Francavilla", "away": "Juve Stabia", "time": "", "league": "Serie C - Groupe C", "country": "ITALIE", "score": {"home": "3", "away": "0"}, "Day": "19/12", "Ended": true}, {"home": "Urawa", "away": "Oita", "time": "", "league": "Coupe de l'Empereur", "country": "JAPON", "score": {"home": "2", "away": "1"}, "Day": "19/12", "Ended": true}, {"home": "Gudja", "away": "Hibernians", "time": "", "league": "Premier League", "country": "MALTE", "score": {"home": "1", "away": "2"}, "Day": "19/12", "Ended": true}, {"home": "Floriana", "away": "Sliema", "time": "", "league": "Premier League", "country": "MALTE", "score": {"home": "2", "away": "0"}, "Day": "19/12", "Ended": true}, {"home": "Balzan", "away": "Valletta", "time": "", "league": "Premier League", "country": "MALTE", "score": {"home": "2", "away": "1"}, "Day": "19/12", "Ended": true}, {"home": "Jeunesse Sportive Soualem", "away": "Youssoufia Berrechid", "time": "", "league": "Botola Pro", "country": "MAROC", "score": {"home": "1", "away": "2"}, "Day": "19/12", "Ended": true}, {"home": "Khouribga", "away": "Maghreb Fez", "time": "", "league": "Botola Pro", "country": "MAROC", "score": {"home": "0", "away": "0"}, "Day": "19/12", "Ended": true}, {"home": "Tanger", "away": "Safi", "time": "", "league": "Botola Pro", "country": "MAROC", "score": {"home": "0", "away": "0"}, "Day": "19/12", "Ended": false}, {"home": "Atlante", "away": "Tampico Madero", "time": "", "league": "Liga de Expansion MX - Ouverture - Phase Finale", "country": "MEXIQUE", "score": {"home": "3", "away": "0"}, "Day": "19/12", "Ended": true}, {"home": "USA", "away": "Bosnie Herzégovine", "time": "", "league": "Amical International", "country": "MONDE", "score": {"home": "1", "away": "0"}, "Day": "19/12", "Ended": true}, {"home": "SJK Akatemia (Fin)", "away": "VIFK (Fin)", "time": "", "league": "Amical Club", "country": "MONDE", "score": {"home": "2", "away": "0"}, "Day": "19/12", "Ended": true}, {"home": "Costa Rica -17 F", "away": "Panama -17 F", "time": "", "league": "Amical International - Femmes", "country": "MONDE", "score": {"home": "1", "away": "1"}, "Day": "19/12", "Ended": true}, {"home": "Esteli", "away": "Diriangen", "time": "", "league": "Liga Primera - Ouverture - Vainqueurs", "country": "NICARAGUA", "score": {"home": "0", "away": "0"}, "Day": "19/12", "Ended": true}, {"home": "Niger", "away": "Plateau", "time": "", "league": "NPFL", "country": "NIGÉRIA", "score": {"home": "1", "away": "0"}, "Day": "19/12", "Ended": true}, {"home": "Gombe", "away": "Shooting Stars", "time": "", "league": "NPFL", "country": "NIGÉRIA", "score": {"home": "0", "away": "0"}, "Day": "19/12", "Ended": true}, {"home": "Akwa United", "away": "Kano", "time": "", "league": "NPFL", "country": "NIGÉRIA", "score": {"home": "3", "away": "0"}, "Day": "19/12", "Ended": true}, {"home": "Enyimba", "away": "Abia Warriors", "time": "", "league": "NPFL", "country": "NIGÉRIA", "score": {"home": "2", "away": "1"}, "Day": "19/12", "Ended": true}, {"home": "Heartland", "away": "Nasarawa", "time": "", "league": "NPFL", "country": "NIGÉRIA", "score": {"home": "3", "away": "3"}, "Day": "19/12", "Ended": true}, {"home": "Katsina Utd", "away": "Enugu", "time": "", "league": "NPFL", "country": "NIGÉRIA", "score": {"home": "1", "away": "2"}, "Day": "19/12", "Ended": true}, {"home": "Kwara", "away": "Dakkada FC", "time": "", "league": "NPFL", "country": "NIGÉRIA", "score": {"home": "3", "away": "0"}, "Day": "19/12", "Ended": true}, {"home": "Lobi Stars", "away": "Rivers United", "time": "", "league": "NPFL", "country": "NIGÉRIA", "score": {"home": "1", "away": "1"}, "Day": "19/12", "Ended": true}, {"home": "Leczna", "away": "Zaglebie", "time": "", "league": "Ekstraklasa", "country": "POLOGNE", "score": {"home": "2", "away": "1"}, "Day": "19/12", "Ended": true}, {"home": "Lech", "away": "Gornik Z.", "time": "", "league": "Ekstraklasa", "country": "POLOGNE", "score": {"home": "2", "away": "1"}, "Day": "19/12", "Ended": true}, {"home": "Legia", "away": "Radomiak Radom", "time": "", "league": "Ekstraklasa", "country": "POLOGNE", "score": {"home": "0", "away": "3"}, "Day": "19/12", "Ended": true}, {"home": "Benfica", "away": "Maritimo", "time": "", "league": "Liga Portugal", "country": "PORTUGAL", "score": {"home": "7", "away": "1"}, "Day": "19/12", "Ended": true}, {"home": "Boavista", "away": "Moreirense", "time": "", "league": "Liga Portugal", "country": "PORTUGAL", "score": {"home": "1", "away": "0"}, "Day": "19/12", "Ended": true}, {"home": "Vizela", "away": "FC Porto", "time": "", "league": "Liga Portugal", "country": "PORTUGAL", "score": {"home": "0", "away": "4"}, "Day": "19/12", "Ended": false}, {"home": "Braga", "away": "Belenenses", "time": "22:00", "league": "Liga Portugal", "country": "PORTUGAL", "score": {"home": "-", "away": "-"}, "Day": "19/12", "Ended": "unKnown"}, {"home": "Penafiel", "away": "Estrela", "time": "", "league": "Liga Portugal 2", "country": "PORTUGAL", "score": {"home": "0", "away": "2"}, "Day": "19/12", "Ended": true}, {"home": "Casa Pia", "away": "Rio Ave", "time": "", "league": "Liga Portugal 2", "country": "PORTUGAL", "score": {"home": "0", "away": "1"}, "Day": "19/12", "Ended": true}, {"home": "FC Porto B", "away": "Academico Viseu", "time": "", "league": "Liga Portugal 2", "country": "PORTUGAL", "score": {"home": "1", "away": "0"}, "Day": "19/12", "Ended": true}, {"home": "Liberec", "away": "Ceske Budejovice", "time": "", "league": "1. Liga", "country": "RÉPUBLIQUE TCHÈQUE", "score": {"home": "0", "away": "0"}, "Day": "19/12", "Ended": true}, {"home": "Sigma Olomouc", "away": "Zlin", "time": "", "league": "1. Liga", "country": "RÉPUBLIQUE TCHÈQUE", "score": {"home": "1", "away": "1"}, "Day": "19/12", "Ended": true}, {"home": "Teplice", "away": "Mlada Boleslav", "time": "", "league": "1. Liga", "country": "RÉPUBLIQUE TCHÈQUE", "score": {"home": "0", "away": "1"}, "Day": "19/12", "Ended": true}, {"home": "Ostrava", "away": "Slavia Prague", "time": "", "league": "1. Liga", "country": "RÉPUBLIQUE TCHÈQUE", "score": {"home": "3", "away": "3"}, "Day": "19/12", "Ended": true}, {"home": "Academica Clinceni", "away": "Chindia Targoviste", "time": "", "league": "Liga 1", "country": "ROUMANIE", "score": {"home": "0", "away": "1"}, "Day": "19/12", "Ended": true}, {"home": "CFR Cluj", "away": "FC Arges", "time": "", "league": "Liga 1", "country": "ROUMANIE", "score": {"home": "1", "away": "0"}, "Day": "19/12", "Ended": true}, {"home": "Sepsi Sf. Gheorghe", "away": "FCSB", "time": "", "league": "Liga 1", "country": "ROUMANIE", "score": {"home": "0", "away": "0"}, "Day": "19/12", "Ended": true}, {"home": "Radnik", "away": "Mladost", "time": "", "league": "Super Liga", "country": "SERBIE", "score": {"home": "0", "away": "2"}, "Day": "19/12", "Ended": true}, {"home": "FK Vozdovac", "away": "Metalac", "time": "", "league": "Super Liga", "country": "SERBIE", "score": {"home": "5", "away": "2"}, "Day": "19/12", "Ended": true}, {"home": "Zilina", "away": "Slovan Bratislava", "time": "", "league": "Fortuna liga", "country": "SLOVAQUIE", "score": {"home": "1", "away": "1"}, "Day": "19/12", "Ended": true}, {"home": "Lugano", "away": "Young Boys", "time": "", "league": "Super League", "country": "SUISSE", "score": {"home": "0", "away": "5"}, "Day": "19/12", "Ended": true}, {"home": "Bale", "away": "Grasshoppers", "time": "", "league": "Super League", "country": "SUISSE", "score": {"home": "2", "away": "2"}, "Day": "19/12", "Ended": true}, {"home": "Sion", "away": "Lausanne", "time": "", "league": "Super League", "country": "SUISSE", "score": {"home": "2", "away": "0"}, "Day": "19/12", "Ended": true}, {"home": "Winterthur", "away": "Vaduz", "time": "", "league": "Challenge League", "country": "SUISSE", "score": {"home": "2", "away": "3"}, "Day": "19/12", "Ended": true}, {"home": "Hang Yuen", "away": "CPC", "time": "", "league": "Premier League", "country": "TAÏWAN", "score": {"home": "3", "away": "0"}, "Day": "19/12", "Ended": true}, {"home": "NTUS", "away": "Zhanyi Skywalkers", "time": "", "league": "Premier League", "country": "TAÏWAN", "score": {"home": "0", "away": "0"}, "Day": "19/12", "Ended": true}, {"home": "Taipei Tatung", "away": "Taichung", "time": "", "league": "Premier League", "country": "TAÏWAN", "score": {"home": "1", "away": "3"}, "Day": "19/12", "Ended": true}, {"home": "Taipower", "away": "Taiwan Steel", "time": "", "league": "Premier League", "country": "TAÏWAN", "score": {"home": "0", "away": "1"}, "Day": "19/12", "Ended": true}, {"home": "Rizespor", "away": "Yeni Malatyaspor", "time": "", "league": "Super Lig", "country": "TURQUIE", "score": {"home": "1", "away": "0"}, "Day": "19/12", "Ended": true}, {"home": "Goztepe", "away": "Karagumruk", "time": "", "league": "Super Lig", "country": "TURQUIE", "score": {"home": "0", "away": "1"}, "Day": "19/12", "Ended": true}, {"home": "Kayserispor", "away": "Gaziantep", "time": "", "league": "Super Lig", "country": "TURQUIE", "score": {"home": "0", "away": "0"}, "Day": "19/12", "Ended": true}, {"home": "Fenerbahce", "away": "Besiktas", "time": "", "league": "Super Lig", "country": "TURQUIE", "score": {"home": "2", "away": "2"}, "Day": "19/12", "Ended": true}, {"home": "Genclerbirligi", "away": "Menemenspor", "time": "", "league": "1. Lig", "country": "TURQUIE", "score": {"home": "5", "away": "0"}, "Day": "19/12", "Ended": true}, {"home": "Bursaspor", "away": "Bandirmaspor", "time": "", "league": "1. Lig", "country": "TURQUIE", "score": {"home": "0", "away": "1"}, "Day": "19/12", "Ended": true}, {"home": "Tuzlaspor", "away": "Manisa FK", "time": "", "league": "1. Lig", "country": "TURQUIE", "score": {"home": "0", "away": "1"}, "Day": "19/12", "Ended": true}, {"home": "Kocaelispor", "away": "Eyupspor", "time": "", "league": "1. Lig", "country": "TURQUIE", "score": {"home": "1", "away": "1"}, "Day": "19/12", "Ended": true}]